{
  "main": {
    "id": "bc99804ce316bfff",
    "type": "split",
    "children": [
      {
        "id": "1043e2e40d307ce8",
        "type": "tabs",
        "children": [
          {
            "id": "b26fa60a04768349",
            "type": "leaf",
            "state": {
              "type": "markdown",
              "state": {
                "file": "RPG/Soleia - World/Brainstorm.md",
                "mode": "source",
                "source": false
              },
              "icon": "lucide-file",
              "title": "Brainstorm"
            }
          },
          {
            "id": "eae75e9878f072cf",
            "type": "leaf",
            "state": {
              "type": "markdown",
              "state": {
                "file": "RPG/Soleia - World/Panteão/Lyrena, a Deusa da Lua e das Águas.md",
                "mode": "source",
                "source": false
              },
              "icon": "lucide-file",
              "title": "Lyrena, a Deusa da Lua e das Águas"
            }
          },
          {
            "id": "6b37a1f63c94e26e",
            "type": "leaf",
            "state": {
              "type": "diff-view",
              "state": {
                "file": "Topcon/Tickets/Divergencia custo dos insumos.md",
                "staged": true
              },
              "icon": "git-pull-request",
              "title": "Diff View (Divergencia custo dos insumos)"
            }
          }
        ],
        "currentTab": 1
      }
    ],
    "direction": "vertical"
  },
  "left": {
    "id": "71c1bbd392f49e2b",
    "type": "split",
    "children": [
      {
        "id": "6f14aecf559f4df0",
        "type": "tabs",
        "children": [
          {
            "id": "b14829de6fa6114c",
            "type": "leaf",
            "state": {
              "type": "markdown",
              "state": {
                "file": "Agenda/2025/03/29 de mar.md",
                "mode": "source",
                "source": false
              },
              "icon": "lucide-file",
              "title": "29 de mar"
            }
          }
        ]
      },
      {
        "id": "c37c7040f36960f1",
        "type": "tabs",
        "children": [
          {
            "id": "f7aafedb8ecd4826",
            "type": "leaf",
            "state": {
              "type": "file-explorer",
              "state": {
                "sortOrder": "alphabetical",
                "autoReveal": false
              },
              "icon": "lucide-folder-closed",
              "title": "Files"
            }
          },
          {
            "id": "fcd35efdd9e2d536",
            "type": "leaf",
            "state": {
              "type": "search",
              "state": {
                "query": "",
                "matchingCase": false,
                "explainSearch": false,
                "collapseAll": false,
                "extraContext": false,
                "sortOrder": "alphabetical"
              },
              "icon": "lucide-search",
              "title": "Search"
            }
          },
          {
            "id": "854c751d9273387c",
            "type": "leaf",
            "state": {
              "type": "bookmarks",
              "state": {},
              "icon": "lucide-bookmark",
              "title": "Bookmarks"
            }
          }
        ]
      }
    ],
    "direction": "horizontal",
    "width": 300
  },
  "right": {
    "id": "f20d81869eb99629",
    "type": "split",
    "children": [
      {
        "id": "5caf6c92dd624a50",
        "type": "tabs",
        "children": [
          {
            "id": "155929a011882c0a",
            "type": "leaf",
            "state": {
              "type": "calendar",
              "state": {},
              "icon": "lucide-file",
              "title": "Plugin no longer active"
            }
          },
          {
            "id": "080f873b6b5f13e8",
            "type": "leaf",
            "state": {
              "type": "git-view",
              "state": {},
              "icon": "git-pull-request",
              "title": "Source Control"
            }
          },
          {
            "id": "87c74fde82584dc7",
            "type": "leaf",
            "state": {
              "type": "backlink",
              "state": {
                "file": "2024/18 de dez.md",
                "collapseAll": false,
                "extraContext": false,
                "sortOrder": "alphabetical",
                "showSearch": false,
                "searchQuery": "",
                "backlinkCollapsed": false,
                "unlinkedCollapsed": true
              },
              "icon": "links-coming-in",
              "title": "Backlinks for 18 de dez"
            }
          },
          {
            "id": "7036a91f401a2d22",
            "type": "leaf",
            "state": {
              "type": "outgoing-link",
              "state": {
                "file": "2024/18 de dez.md",
                "linksCollapsed": false,
                "unlinkedCollapsed": true
              },
              "icon": "links-going-out",
              "title": "Outgoing links from 18 de dez"
            }
          },
          {
            "id": "ff19de66dd06a945",
            "type": "leaf",
            "state": {
              "type": "tag",
              "state": {
                "sortOrder": "frequency",
                "useHierarchy": true
              },
              "icon": "lucide-tags",
              "title": "Tags"
            }
          },
          {
            "id": "7e14212bd7f7de14",
            "type": "leaf",
            "state": {
              "type": "outline",
              "state": {
                "file": "2024/18 de dez.md"
              },
              "icon": "lucide-list",
              "title": "Outline of 18 de dez"
            }
          },
          {
            "id": "74b7b31ca09c9ae5",
            "type": "leaf",
            "state": {
              "type": "planner-timeline",
              "state": {},
              "icon": "lucide-file",
              "title": "Plugin no longer active"
            }
          }
        ],
        "currentTab": 1
      }
    ],
    "direction": "horizontal",
    "width": 300
  },
  "left-ribbon": {
    "hiddenItems": {
      "obsidian-5e-statblocks:Open Creature pane": false,
      "obsidian-leaflet-plugin:Open Leaflet Map": false,
      "switcher:Open quick switcher": false,
      "graph:Open graph view": false,
      "canvas:Create new canvas": false,
      "daily-notes:Open today's daily note": false,
      "templates:Insert template": false,
      "command-palette:Open command palette": false,
      "obsidian-git:Open Git source control": false,
      "templater-obsidian:Templater": false
    }
  },
  "active": "eae75e9878f072cf",
  "lastOpenFiles": [
    "RPG/Soleia - World/Panteão/Anexos/590a2161-2c93-46e5-86f9-fdfce720b40fmatheus-teixeira.jpg",
    "RPG/Soleia - World/Panteão/Anexos",
    "RPG/Soleia - World/Ideias gerais do mundo.md",
    "RPG/Soleia - World/Definições básicas do cenário.md",
    "RPG/Soleia - World/Locais/Outros/Jardim Secreto de Aeglíria.md",
    "Agenda/2025/03/28 de mar.md",
    "conflict-files-obsidian-git.md",
    "RPG/Soleia - World/NPCs/Rei das Flores.md",
    "Conselho das Flores.md",
    "RPG/Soleia - World/Locais/Aeglíria.md",
    "Agenda/2025/03/29 de mar.md",
    "Agenda/2025/03/27 de mar.md",
    "Agenda/2025/03/26 de mar.md",
    "Agenda/2025/03/25 de mar.md",
    "Agenda/2025/03/24 de mar.md",
    "RPG/Soleia - World/NPCs/Anexos/Pasted image 20250328002530.png",
    "RPG/Soleia - World/NPCs/Anexos",
    "RPG/Soleia - World/Locais/Outros/Anexos/Pasted image 20250328000322.png",
    "RPG/Soleia - World/Locais/Outros/Anexos/DALL·E 2025-03-27 23.43.54 - A mystical secret garden hidden deep underground, illuminated by soft bioluminescent plants and glowing crystals. The garden features a circular clear.png",
    "RPG/Soleia - World/Locais/Outros/Anexos/DALL·E 2025-03-27 23.43.54 - A mystical secret garden hidden deep underground, illuminated by soft bioluminescent plants and glowing crystals. The garden features a circular clear.webp",
    "RPG/Soleia - World/Locais/Outros/Anexos",
    "RPG/Soleia - World/Items/Materiais/Flor Perene.md",
    "RPG/Soleia - World/Locais/Lumindor.md",
    "RPG/Soleia - World/Locais/Thundralis.md",
    "RPG/Soleia - World/Locais/Terramor.md",
    "RPG/Soleia - World/Locais/Aurélia.md",
    "Topcon/Tickets/Remessa 2724 - TOPCON.md",
    "Topcon/Tickets/Não conclui programação NewDispatch - Concreserv.md",
    "Topcon/Tickets/Notas sem chave.md",
    "Topcon/Helper.md",
    "Templates/RPG/Masmorra.md",
    "Templates/RPG/Item.md",
    "Templates/Daily.md",
    "RPG/Soleia - World/Items/Materiais",
    "RPG/Soleia - World/Items",
    "Templates/Topcon",
    "Templates/RPG",
    "RPG/Attachments/Caelum Thornfield.png",
    "Agenda/2025/03",
    "RPG/Tables",
    "Topcon/Tickets/Anexos/Ticket 478213 - 3.png",
    "Topcon/Tickets/Anexos/Ticket 478213 - 2.png",
    "Topcon/Tickets/Anexos/Ticket 478213 - 1.png",
    "Topcon/Tickets/Anexos",
    "RPG/Attachments/valandra.png",
    "RPG/Attachments/pena_dourada (1).png"
  ]
}